sdw_tools/MetricCalculator.py
sdw_tools/RepoScraper.py
sdw_tools/__init__.py
sdw_tools/backlog_inversion.py
sdw_tools/duplicate_work.py
sdw_tools/ffr.py
sdw_tools/pdi.py
sdw_tools/stale_forks.py
sdw_tools/utils.py
sdw_tools-0.1.0.dist-info/LICENSE
sdw_tools-0.1.0.dist-info/METADATA
sdw_tools-0.1.0.dist-info/WHEEL
sdw_tools-0.1.0.dist-info/top_level.txt
sdw_tools-0.1.0.dist-info/RECORD
