Metadata-Version: 2.1
Name: sdw-tools
Version: 0.1.0
Summary: This library can be used for fetching data from github repositories and calculating the Software Development Waste associated with the repository.
Home-page: https://github.com/DivijD012/sdw_tools
Author: D
Author-email: divij.d@students.iiit.ac.in
License: UNKNOWN
Platform: UNKNOWN
Classifier: Programming Language :: Python :: 3
Classifier: License :: OSI Approved :: MIT License
Classifier: Operating System :: OS Independent
Requires-Python: >=3.6
Requires-Dist: matplotlib
Requires-Dist: numpy
Requires-Dist: requests
Requires-Dist: scikit-learn
